geometry/__init__.py
geometry/config.py
geometry/core.py
geometry/curve/__init__.py
geometry/curve/ellipse.py
geometry/curve/splines.py
geometry/curve/subdivisions.py
geometry/internal.py
geometry/intersections.py
geometry/mesh/__init__.py
geometry/mesh/base.py
geometry/mesh/rectilinear_mesh.py
geometry/mesh/utilities.py
geometry/mesh/voronoi_mesh.py
geometry/point.py
geometry/shape/__init__.py
geometry/shape/base.py
geometry/shape/convex_polytope.py
geometry/shape/hypersphere.py
geometry/shape/iso_hyperrectangle.py
geometry/shape/utlities.py
geometry/transformations.py
geometry/triangulation.py
geometry/utilities.py
geometry/validators.py
geometry/vector.py
python_geometry-0.5.0.dist-info/LICENSE
python_geometry-0.5.0.dist-info/WHEEL
python_geometry-0.5.0.dist-info/METADATA
python_geometry-0.5.0.dist-info/RECORD
