Metadata-Version: 2.1
Name: python-geometry
Version: 0.5.0
Summary: Geometry in Python.
License: MIT
Author: Dominik Steinberger
Author-email: dominik.steinberger@imfd.tu-freiberg.de
Requires-Python: >=3.6,<4.0
Classifier: Development Status :: 2 - Pre-Alpha
Classifier: Intended Audience :: Science/Research
Classifier: License :: OSI Approved :: MIT License
Classifier: Programming Language :: Python :: 3
Classifier: Programming Language :: Python :: 3.6
Classifier: Programming Language :: Python :: 3.7
Classifier: Programming Language :: Python :: 3.8
Classifier: Topic :: Scientific/Engineering :: Mathematics
Requires-Dist: attrs (>=19.1,<20.0)
Requires-Dist: numpy (>=1.16,<2.0)
Requires-Dist: scipy (>=1.1,<2.0)
Requires-Dist: triangle (>=20190115.3,<20190116.0)
